{"factionName":"Minions","warlocks":[{"images":["barnabas-lord-of-blood-1.jpg","barnabas-lord-of-blood-2.jpg","barnabas-lord-of-blood-3.jpg","barnabas-lord-of-blood-4.jpg","barnabas-lord-of-blood-5.jpg","barnabas-lord-of-blood-6.jpg"],"title":"Barnabas, Lord of Blood"},{"images":["bloody-barnabas-1.jpg","bloody-barnabas-2.jpg","bloody-barnabas-3.jpg","bloody-barnabas-4.jpg"],"title":"Bloody Barnabas"},{"images":["calaban-the-grave-walker-1.jpg","calaban-the-grave-walker-2.jpg","calaban-the-grave-walker-3.jpg","calaban-the-grave-walker-4.jpg"],"title":"Calaban, the Grave Walker"},{"images":["dr-arkadius-1.jpg","dr-arkadius-2.jpg","dr-arkadius-3.jpg","dr-arkadius-4.jpg"],"title":"Dr. Arkadius"},{"images":["helga-the-conqueror-1.jpg","helga-the-conqueror-2.jpg","helga-the-conqueror-3.jpg","helga-the-conqueror-4.jpg"],"title":"Helga the Conqueror"},{"images":["jaga-jaga-the-death-charmer-1.jpg","jaga-jaga-the-death-charmer-2.jpg","jaga-jaga-the-death-charmer-3.jpg","jaga-jaga-the-death-charmer-4.jpg"],"title":"Jaga-Jaga, the Death Charmer"},{"images":["lord-carver-bmmd-esq-iii-1.jpg","lord-carver-bmmd-esq-iii-2.jpg","lord-carver-bmmd-esq-iii-3.jpg","lord-carver-bmmd-esq-iii-4.jpg"],"title":"Lord Carver, BMMD, Esq. III"},{"images":["maelok-the-dreadbound-1.jpg","maelok-the-dreadbound-2.jpg","maelok-the-dreadbound-3.jpg","maelok-the-dreadbound-4.jpg"],"title":"Maelok the Dreadbound"},{"images":["midas-1.jpg","midas-2.jpg","midas-3.jpg","midas-4.jpg"],"title":"Midas"},{"images":["rask-1.jpg","rask-2.jpg","rask-3.jpg","rask-4.jpg"],"title":"Rask"},{"images":["sturm-drang-1.jpg","sturm-drang-2.jpg","sturm-drang-3.jpg","sturm-drang-4.jpg"],"title":"Sturm & Drang"}],"warbeasts":[{"images":["battle-boar-1.jpg","battle-boar-2.jpg"],"title":"Battle Boar"},{"images":["blackhide-wrastler-1.jpg","blackhide-wrastler-2.jpg"],"title":"Blackhide Wrastler"},{"images":["blind-walker-1.jpg","blind-walker-2.jpg"],"title":"Blind Walker"},{"images":["boneswarm-1.jpg","boneswarm-2.jpg"],"title":"Boneswarm"},{"images":["bull-snapper-1.jpg","bull-snapper-2.jpg"],"title":"Bull Snapper"},{"images":["dracodile-1.jpg","dracodile-2.jpg","dracodile-3.jpg","dracodile-4.jpg"],"title":"Dracodile"},{"images":["gun-boar-1.jpg","gun-boar-2.jpg"],"title":"Gun Boar"},{"images":["ironback-spitter-1.jpg","ironback-spitter-2.jpg"],"title":"Ironback Spitter"},{"images":["razor-boar-1.jpg","razor-boar-2.jpg"],"title":"Razor Boar"},{"images":["road-hog-1.jpg","road-hog-2.jpg"],"title":"Road Hog"},{"images":["splatter-boar-1.jpg","splatter-boar-2.jpg"],"title":"Splatter Boar"},{"images":["swamp-horror-1.jpg","swamp-horror-2.jpg"],"title":"Swamp Horror"},{"images":["war-hog-1.jpg","war-hog-2.jpg"],"title":"War Hog"}],"units":[{"images":["bog-trog-ambushers-1.jpg","bog-trog-ambushers-2.jpg"],"title":"Bog Trog Ambushers"},{"images":["boil-master-spirit-cauldron-1.jpg","boil-master-spirit-cauldron-2.jpg"],"title":"Boil Master & Spirit Cauldron"},{"images":["croak-raiders-1.jpg","croak-raiders-2.jpg"],"title":"Croak Raiders"},{"images":["croak-trappers-1.jpg","croak-trappers-2.jpg"],"title":"Croak Trappers"},{"images":["farrow-bone-grinders-1.jpg","farrow-bone-grinders-2.jpg"],"title":"Farrow Bone Grinders"},{"images":["farrow-brigand-warlord-1.jpg","farrow-brigand-warlord-2.jpg"],"title":"Farrow Brigand Warlord"},{"images":["farrow-brigands-1.jpg","farrow-brigands-2.jpg"],"title":"Farrow Brigands"},{"images":["farrow-commandos-1.jpg","farrow-commandos-2.jpg"],"title":"Farrow Commandos"},{"images":["farrow-razorback-crew-1.jpg","farrow-razorback-crew-2.jpg"],"title":"Farrow Razorback Crew"},{"images":["farrow-slaughterhousers-1.jpg","farrow-slaughterhousers-2.jpg"],"title":"Farrow Slaughterhousers"},{"images":["farrow-valkyries-1.jpg","farrow-valkyries-2.jpg"],"title":"Farrow Valkyries"},{"images":["gatorman-bokor-bog-trog-swamp-shamblers-1.jpg","gatorman-bokor-bog-trog-swamp-shamblers-2.jpg"],"title":"Gatorman Bokor & Bog Trog Swamp Shamblers"},{"images":["gatorman-posse-1.jpg","gatorman-posse-2.jpg"],"title":"Gatorman Posse"},{"images":["gatorman-posse-blindwater-1.jpg","gatorman-posse-blindwater-2.jpg"],"title":"Gatorman Posse (Blindwater)"},{"images":["lynus-wesselbaum-edrea-lloryrr-1.jpg","lynus-wesselbaum-edrea-lloryrr-2.jpg"],"title":"Lynus Wesselbaum & Edrea Lloryrr"},{"images":["swamp-gobber-bellows-crew-1.jpg","swamp-gobber-bellows-crew-2.jpg"],"title":"Swamp Gobber Bellows Crew"},{"images":["void-leech-1.jpg","void-leech-2.jpg"],"title":"Void Leech"}],"solos":[{"images":["agata-queen-of-carnage-1.jpg","agata-queen-of-carnage-2.jpg"],"title":"Agata, Queen of Carnage"},{"images":["alten-ashley-1.jpg","alten-ashley-2.jpg"],"title":"Alten Ashley"},{"images":["bog-trog-mist-speaker-1.jpg","bog-trog-mist-speaker-2.jpg"],"title":"Bog Trog Mist Speaker"},{"images":["bog-trog-trawler-1.jpg","bog-trog-trawler-2.jpg"],"title":"Bog Trog Trawler"},{"images":["bone-shrine-1.jpg","bone-shrine-2.jpg"],"title":"Bone Shrine"},{"images":["brun-cragback-lug-1.jpg","brun-cragback-lug-2.jpg","brun-cragback-lug-3.jpg","brun-cragback-lug-4.jpg"],"title":"Brun Cragback & Lug"},{"images":["croak-hunter-1.jpg","croak-hunter-2.jpg"],"title":"Croak Hunter"},{"images":["dahlia-hallyr-skarath-1.jpg","dahlia-hallyr-skarath-2.jpg","dahlia-hallyr-skarath-3.jpg","dahlia-hallyr-skarath-4.jpg"],"title":"Dahlia Hallyr & Skarath"},{"images":["efaarit-scouts-1.jpg","efaarit-scouts-2.jpg"],"title":"Efaarit Scouts"},{"images":["feralgeist-1.jpg","feralgeist-2.jpg"],"title":"Feralgeist"},{"images":["gatorman-husk-1.jpg","gatorman-husk-2.jpg"],"title":"Gatorman Husk"},{"images":["gatorman-soul-slave-1.jpg","gatorman-soul-slave-2.jpg"],"title":"Gatorman Soul Slave"},{"images":["gatorman-witch-doctor-1.jpg","gatorman-witch-doctor-2.jpg"],"title":"Gatorman Witch Doctor"},{"images":["gobber-tinker-1.jpg","gobber-tinker-2.jpg"],"title":"Gobber Tinker"},{"images":["gremlin-swarm-1.jpg","gremlin-swarm-2.jpg"],"title":"Gremlin Swarm"},{"images":["gudrun-the-wanderer-1.jpg","gudrun-the-wanderer-2.jpg"],"title":"Gudrun the Wanderer"},{"images":["hutchuk-ogrun-bounty-hunter-1.jpg","hutchuk-ogrun-bounty-hunter-2.jpg"],"title":"Hutchuk, Ogrun Bounty Hunter"},{"images":["kwaak-slickspine-gub-croak-sorcerers-1.jpg","kwaak-slickspine-gub-croak-sorcerers-2.jpg"],"title":"Kwaak Slickspine & Gub, Croak Sorcerers"},{"images":["lanyssa-ryssyl-nyss-sorceress-1.jpg","lanyssa-ryssyl-nyss-sorceress-2.jpg"],"title":"Lanyssa Ryssyl, Nyss Sorceress"},{"images":["longchops-1.jpg","longchops-2.jpg"],"title":"Longchops"},{"images":["maximus-1.jpg","maximus-2.jpg"],"title":"Maximus"},{"images":["rorsh-brine-1.jpg","rorsh-brine-2.jpg","rorsh-brine-3.jpg","rorsh-brine-4.jpg"],"title":"Rorsh & Brine"},{"images":["saxon-orrik-1.jpg","saxon-orrik-2.jpg"],"title":"Saxon Orrik"},{"images":["swamp-gobber-chef-1.jpg","swamp-gobber-chef-2.jpg"],"title":"Swamp Gobber Chef"},{"images":["targ-1.jpg","targ-2.jpg"],"title":"Targ"},{"images":["thrullg-1.jpg","thrullg-2.jpg"],"title":"Thrullg"},{"images":["totem-hunter-1.jpg","totem-hunter-2.jpg"],"title":"Totem Hunter"},{"images":["viktor-pendrake-1.jpg","viktor-pendrake-2.jpg"],"title":"Viktor Pendrake"},{"images":["wrong-eye-snapjaw-1.jpg","wrong-eye-snapjaw-2.jpg","wrong-eye-snapjaw-3.jpg","wrong-eye-snapjaw-4.jpg"],"title":"Wrong Eye & Snapjaw"}],"factionType":"Hordes"}